Alpha/Globals.py
Alpha/__init__.py
Alpha/helperFunctions.py
Alpha/main.py
Alpha/run_alpha.py
Alpha/assets/Fonts/Arial Unicode.ttf
Alpha/assets/Fonts/Courier New.ttf
Alpha/assets/Fonts/nasalization-rg.otf
Alpha/assets/config files/c7_Michael-et-al-2021.cs
Alpha/assets/config files/demo_commands.txt
Alpha/assets/config files/functions.txt
Alpha/assets/config files/newConfig.cs
Alpha/assets/data files/ECHUS_CHAP_AR1_A.stat
Alpha/assets/data files/Pickering.scc
Alpha/assets/data files/README.md
Alpha/assets/data files/c7_Michael-et-al-2021.scc
Alpha/assets/data files/sample.binned
Alpha/assets/data files/sample.diam
Alpha/assets/data files/sample.r
Alpha/assets/data files/sample.scc
Alpha/assets/data files/sample.stat
Alpha/assets/data files/sample2.diam
Alpha/assets/icons/Craterstats-Icon.ico
Alpha/assets/icons/icon-default.png
Alpha/assets/icons/icon.png
Alpha/assets/log/runtime.csv
Alpha/assets/plots/blank_plot.png
Alpha/gm/__init__.py
Alpha/gm/file/__init__.py
Alpha/gm/file/file_exists.py
Alpha/gm/file/filename.py
Alpha/gm/file/read_textfile.py
Alpha/gm/file/read_textstructure.py
Alpha/gm/file/write_textfile.py
Alpha/gm/idl/__init__.py
Alpha/gm/idl/value_locate.py
Alpha/gm/idl/where.py
Alpha/gm/maths/__init__.py
Alpha/gm/maths/normal.py
Alpha/gm/maths/poisson.py
Alpha/gm/maths/poly.py
Alpha/gm/maths/range.py
Alpha/gm/maths/scl.py
Alpha/gm/plotting/__init__.py
Alpha/gm/plotting/mpl_check_font.py
Alpha/gm/plotting/ticks.py
Alpha/gm/string/__init__.py
Alpha/gm/string/bright.py
Alpha/gm/string/quoted_split.py
Alpha/gm/string/scientific_notation.py
Alpha/gm/string/sigfigs.py
Alpha/gm/string/strip_quotes.py
craterstats_gui-1.0.1.dist-info/LICENSE
craterstats_gui-1.0.1.dist-info/METADATA
craterstats_gui-1.0.1.dist-info/WHEEL
craterstats_gui-1.0.1.dist-info/entry_points.txt
craterstats_gui-1.0.1.dist-info/top_level.txt
craterstats_gui-1.0.1.dist-info/RECORD
