Metadata-Version: 2.1
Name: craterstats_gui
Version: 1.0.1
Summary: A graphical user interface for improving user experience when computing and generating crater statistics.
Home-page: https://github.com/LWATLINGTON02/CraterStats-Capstone/tree/main
Author: Lunar Pit Patrol
Author-email: EPalmisanoConnect@gmail.com
Classifier: Programming Language :: Python :: 3
Classifier: License :: OSI Approved :: MIT License
Classifier: Operating System :: OS Independent
Requires-Python: >=3.8.0
License-File: LICENSE
Requires-Dist: flet
Requires-Dist: craterstats
